scoped/__init__.py
scoped/base.py
scoped_concerns-0.1.1.dist-info/LICENSE
scoped_concerns-0.1.1.dist-info/METADATA
scoped_concerns-0.1.1.dist-info/WHEEL
scoped_concerns-0.1.1.dist-info/top_level.txt
scoped_concerns-0.1.1.dist-info/RECORD
